{"directed": false, "multigraph": false, "graph": {"topTier": 2}, "nodes": [{"northbound": [], "southbound": ["L1_1", "L1_2", "L1_3", "L1_4"], "tier": 2, "ipv4": {}, "isTopTier": true, "id": "T2_1"}, {"northbound": ["T2_1", "T2_2"], "southbound": ["C0_11"], "tier": 1, "ipv4": {"C0_11": "192.168.0.254"}, "isTopTier": false, "id": "L1_1"}, {"northbound": ["T2_1", "T2_2"], "southbound": ["C0_21"], "tier": 1, "ipv4": {"C0_21": "192.168.1.254"}, "isTopTier": false, "id": "L1_2"}, {"northbound": ["T2_1", "T2_2"], "southbound": ["C0_31"], "tier": 1, "ipv4": {"C0_31": "192.168.2.254"}, "isTopTier": false, "id": "L1_3"}, {"northbound": ["T2_1", "T2_2"], "southbound": ["C0_41"], "tier": 1, "ipv4": {"C0_41": "192.168.3.254"}, "isTopTier": false, "id": "L1_4"}, {"northbound": [], "southbound": ["L1_1", "L1_2", "L1_3", "L1_4"], "tier": 2, "ipv4": {}, "isTopTier": true, "id": "T2_2"}, {"northbound": ["L1_1"], "southbound": [], "tier": 0, "ipv4": {"L1_1": "192.168.0.1"}, "isTopTier": false, "id": "C0_11"}, {"northbound": ["L1_2"], "southbound": [], "tier": 0, "ipv4": {"L1_2": "192.168.1.1"}, "isTopTier": false, "id": "C0_21"}, {"northbound": ["L1_3"], "southbound": [], "tier": 0, "ipv4": {"L1_3": "192.168.2.1"}, "isTopTier": false, "id": "C0_31"}, {"northbound": ["L1_4"], "southbound": [], "tier": 0, "ipv4": {"L1_4": "192.168.3.1"}, "isTopTier": false, "id": "C0_41"}], "links": [{"computeNetwork": false, "source": "T2_1", "target": "L1_1"}, {"computeNetwork": false, "source": "T2_1", "target": "L1_2"}, {"computeNetwork": false, "source": "T2_1", "target": "L1_3"}, {"computeNetwork": false, "source": "T2_1", "target": "L1_4"}, {"computeNetwork": false, "source": "L1_1", "target": "T2_2"}, {"computeNetwork": true, "source": "L1_1", "target": "C0_11"}, {"computeNetwork": false, "source": "L1_2", "target": "T2_2"}, {"computeNetwork": true, "source": "L1_2", "target": "C0_21"}, {"computeNetwork": false, "source": "L1_3", "target": "T2_2"}, {"computeNetwork": true, "source": "L1_3", "target": "C0_31"}, {"computeNetwork": false, "source": "L1_4", "target": "T2_2"}, {"computeNetwork": true, "source": "L1_4", "target": "C0_41"}]}